verysimplemodulebjk116/__init__.py
verysimplemodulebjk116/add.py
verysimplemodulebjk116/subtract.py
verysimplemodulebjk116/extras/__init__.py
verysimplemodulebjk116/extras/divide.py
verysimplemodulebjk116/extras/multiply.py
verysimplemodulebjk116-0.0.2.dist-info/METADATA
verysimplemodulebjk116-0.0.2.dist-info/WHEEL
verysimplemodulebjk116-0.0.2.dist-info/top_level.txt
verysimplemodulebjk116-0.0.2.dist-info/RECORD
