Metadata-Version: 2.1
Name: verysimplemodulebjk116
Version: 0.0.2
Summary: My First Python Package TeeHee
Home-page: UNKNOWN
Author: Brian Karab
Author-email: karabinchak.brian@gmail.com
License: UNKNOWN
Keywords: python,first package
Platform: UNKNOWN
Classifier: Development Status :: 3 - Alpha
Classifier: Intended Audience :: Education
Classifier: Programming Language :: Python :: 2
Classifier: Programming Language :: Python :: 3
Classifier: Operating System :: MacOS :: MacOS X
Classifier: Operating System :: Microsoft :: Windows
